{
	"format_version": "1.12.0",
	"minecraft:geometry": [
		{
			"description": {
				"identifier": "geometry.unknown",
				"texture_width": 256,
				"texture_height": 256,
				"visible_bounds_width": 5,
				"visible_bounds_height": 6.5,
				"visible_bounds_offset": [0, 2.75, 0]
			},
			"bones": [
				{
					"name": "Root",
					"pivot": [0, 0, 0]
				},
				{
					"name": "Bark",
					"parent": "Root",
					"pivot": [0, 0, 0],
					"cubes": [
						{"origin": [-8, 0, -8], "size": [16, 14, 16], "uv": [126, 130]},
						{"origin": [-7.5, 14, -7.5], "size": [15, 7, 15], "uv": [150, 26]},
						{"origin": [-7.085, 20.595, -7.085], "size": [14.17, 9.81, 14.17], "uv": [101, 160]},
						{"origin": [-6.5, 30, -6.5], "size": [13, 15, 13], "uv": [0, 156]},
						{"origin": [-7.1177, 28.85233, -6.5], "size": [4, 14, 13], "pivot": [-5.1177, 35.85233, 0], "rotation": [0, 0, 5], "uv": [0, 0]},
						{"origin": [3.1177, 28.85233, -6.5], "size": [4, 14, 13], "pivot": [5.1177, 35.85233, 0], "rotation": [0, 0, -5], "uv": [0, 0], "mirror": true},
						{"origin": [-10.21962, 0.48455, -6.5], "size": [9, 28, 13], "pivot": [-5.71962, 14.48455, 0], "rotation": [0, 0, 10], "uv": [57, 146]},
						{"origin": [1.21962, 0.48455, -6.5], "size": [9, 28, 13], "pivot": [5.71962, 14.48455, 0], "rotation": [0, 0, -10], "uv": [57, 146], "mirror": true},
						{"origin": [0, 38.5, -8], "size": [0, 1, 2], "uv": [0, 0]},
						{"origin": [-0.5, 38.2, -8], "size": [1, 1, 0], "uv": [0, 3]}
					]
				},
				{
					"name": "Leaves",
					"parent": "Bark",
					"pivot": [0, 44, 0],
					"cubes": [
						{"origin": [-18.5, 45, -19], "size": [37, 28, 38], "uv": [0, 0]},
						{"origin": [-15.5, 48, -23], "size": [31, 22, 4], "uv": [112, 0]},
						{"origin": [-15.5, 48, 19], "size": [31, 22, 4], "uv": [112, 0]},
						{"origin": [-25.1638, 39.76459, -10], "size": [16, 19, 20], "pivot": [-17.1638, 49.26459, 0], "rotation": [0, 0, -20], "uv": [70, 107]},
						{"origin": [9.1638, 39.76459, -10], "size": [16, 19, 20], "pivot": [17.1638, 49.26459, 0], "rotation": [0, 0, 20], "uv": [70, 107], "mirror": true},
						{"origin": [-11, 39, 5], "size": [22, 6, 13], "uv": [122, 107]},
						{"origin": [-13, 40, 6], "size": [2, 7, 11], "uv": [0, 66]},
						{"origin": [11, 40, 6], "size": [2, 7, 11], "uv": [0, 66], "mirror": true},
						{"origin": [-9, 37, 6], "size": [18, 2, 11], "uv": [139, 55]},
						{"origin": [-22.5, 48, -15], "size": [4, 22, 31], "uv": [0, 103]},
						{"origin": [18.5, 48, -15], "size": [4, 22, 31], "uv": [0, 103], "mirror": true},
						{"origin": [-15.5, 72, -17], "size": [31, 4, 33], "uv": [95, 70]},
						{"origin": [-15.5, 44, -17], "size": [31, 4, 33], "uv": [0, 66]}
					]
				},
				{
					"name": "Poster",
					"parent": "Bark",
					"pivot": [0, 39, -6.51],
					"cubes": [
						{"origin": [-6.5, 25.02664, -7.12009], "size": [13, 14, 0], "pivot": [0, 32.02664, -7.12009], "rotation": [-5, 0, 0], "uv": [0, 84]}
					]
				}
			]
		}
	]
}